TimeSeriesInterpretorRNN/__init__.py
TimeSeriesInterpretorRNN/main.py
TimeSeriesInterpretorRNN-0.0.11.dist-info/LICENSE
TimeSeriesInterpretorRNN-0.0.11.dist-info/METADATA
TimeSeriesInterpretorRNN-0.0.11.dist-info/WHEEL
TimeSeriesInterpretorRNN-0.0.11.dist-info/top_level.txt
TimeSeriesInterpretorRNN-0.0.11.dist-info/RECORD
