Metadata-Version: 2.1
Name: TimeSeriesInterpretorRNN
Version: 0.0.11
Summary: UNKNOWN
Home-page: UNKNOWN
Author: Dara Sravan Kumar
Author-email: <sravandara007@gmail.com>
License: UNKNOWN
Keywords: RNNInterpretor,TimeSeriesInterpretor,TimeSeriesRNNInterpretor
Platform: UNKNOWN
Classifier: Programming Language :: Python :: 3
Classifier: Operating System :: Unix
Classifier: Operating System :: MacOS :: MacOS X
Classifier: Operating System :: Microsoft :: Windows
License-File: LICENSE
Requires-Dist: tensorflow (==2.2)
Requires-Dist: numpy
Requires-Dist: shap (==0.39.0)
Requires-Dist: pandas
Requires-Dist: plotly
